{"UUID":"82aa9260-78b4-0139-a61a-5a5f89656090","Players":["Player 1: X","Computer: O"],"Moves":[[1,0],[0,0],[0,1],[1,1],[2,2],[0,2],[2,0],[2,1],[1,2]],"Winner":"Draw"}
{"UUID":"842e41a0-78b4-0139-a61b-5a5f89656090","Players":["Computer: X","Player 1: O"],"Moves":[[0,1],[0,0],[1,0],[1,1],[2,2],[0,2],[2,0],[2,1],[1,2]],"Winner":"Draw"}
{"UUID":"84ae7ce0-78b4-0139-a61c-5a5f89656090","Players":["Computer: X","Player 1: O"],"Moves":[[2,2],[1,1],[0,0],[0,1],[2,1],[2,0],[0,2],[1,2],[1,0]],"Winner":"Draw"}
{"UUID":"852259f0-78b4-0139-a61d-5a5f89656090","Players":["Computer: X","Player 1: O"],"Moves":[[1,0],[0,0],[0,1],[1,1],[2,2],[0,2],[2,0],[2,1],[1,2]],"Winner":"Draw"}
{"UUID":"85b4fc90-78b4-0139-a61e-5a5f89656090","Players":["Computer: X","Player 1: O"],"Moves":[[1,0],[0,0],[0,1],[1,1],[2,2],[0,2],[2,0],[2,1],[1,2]],"Winner":"Draw"}{"UUID":"b58d20d0-78b4-0139-a621-5a5f89656090","Players":["Player 1: X","Computer: O"],"Moves":[[2,1],[0,1],[0,0],[2,0],[0,2],[1,1],[1,0],[1,2],[2,2]],"Winner":"Draw"}
{"UUID":"b72cbb30-78b4-0139-a622-5a5f89656090","Players":["Computer: X","Player 1: O"],"Moves":[[2,0],[1,1],[0,0],[1,0],[1,2],[0,1],[2,1],[2,2],[0,2]],"Winner":"Draw"}
{"UUID":"b7a28320-78b4-0139-a623-5a5f89656090","Players":["Player 1: X","Computer: O"],"Moves":[[2,1],[0,1],[0,0],[2,0],[0,2],[1,1],[1,0],[1,2],[2,2]],"Winner":"Draw"}
{"UUID":"b826e660-78b4-0139-a624-5a5f89656090","Players":["Computer: X","Player 1: O"],"Moves":[[0,0],[1,1],[0,1],[0,2],[2,0],[1,0],[1,2],[2,1],[2,2]],"Winner":"Draw"}
{"UUID":"b89aa5e0-78b4-0139-a625-5a5f89656090","Players":["Player 1: X","Computer: O"],"Moves":[[2,1],[0,1],[0,0],[2,0],[0,2],[1,1],[1,0],[1,2],[2,2]],"Winner":"Draw"}
